[{"id":"1776598961335","type":"expense","account":"信用卡-中信卡","date":"2026-04-19","category":"餐點-飲品","note":"礦泉水+16茶","amount":57,"currency":"TWD"},{"id":"1776598998331","type":"expense","account":"信用卡-中信卡","date":"2026-04-19","category":"餐點-午餐","note":"樂麵屋-拉麵","amount":500,"currency":"TWD"},{"id":"1776599117516","type":"expense","account":"信用卡-中信卡","date":"2026-04-19","category":"餐點-晚餐","note":"京都御握丸","amount":370,"currency":"TWD"},{"id":"1776599153710","type":"expense","account":"信用卡-中信卡","date":"2026-04-19","category":"餐點-晚餐","note":"壽司+蛋包飯飯糰","amount":117,"currency":"TWD"},{"id":"1776599237779","type":"expense","account":"信用卡-中信卡","date":"2026-04-19","category":"餐點-飲品","note":"日東紅茶-焙香煎茶歐蕾","amount":39,"currency":"TWD"},{"id":"1776645972530","type":"expense","account":"信用卡-中信卡","date":"2026-04-20","category":"餐點-飲品","note":"檸檬紅茶+比菲多","amount":78,"currency":"TWD"},{"id":"1776708508101","type":"expense","account":"信用卡-中信卡","date":"2026-04-20","category":"交通-加油","note":"無備註","amount":145,"currency":"TWD"},{"id":"1776768233663","type":"expense","account":"信用卡-中信卡","date":"2026-04-21","category":"餐點-飲品","note":"檸檬紅茶+比菲多","amount":78,"currency":"TWD"},{"id":"1776819565422","type":"expense","account":"現金","date":"2026-04-22","category":"餐點-午餐","note":"炒麵","amount":80,"currency":"TWD"},{"id":"1776819586219","type":"expense","account":"信用卡-中信卡","date":"2026-04-22","category":"餐點-飲品","note":"梅子綠茶+比菲多","amount":78,"currency":"TWD"},{"id":"1776878888441","type":"expense","account":"現金","date":"2026-04-22","category":"交通-保修","note":"換機油+空汙濾網","amount":550,"currency":"TWD"},{"id":"1776933915092","type":"expense","account":"信用卡-中信卡","date":"2026-04-23","category":"餐點-飲品","note":"梅子綠茶+比菲多","amount":78,"currency":"TWD"},{"id":"1776944633885","type":"expense","account":"現金","date":"2026-04-23","category":"餐點-晚餐","note":"滷味","amount":95,"currency":"TWD"},{"id":"1777097503474","type":"expense","account":"信用卡-中信卡","date":"2026-04-24","category":"餐點-午餐","note":"滿漢大餐+科學麵","amount":65,"currency":"TWD"},{"id":"1777097567582","type":"expense","account":"信用卡-中信卡","date":"2026-04-24","category":"餐點-飲品","note":"檸檬紅茶+比菲多+原萃玄米茶","amount":100,"currency":"TWD"},{"id":"1777136291054","type":"expense","account":"信用卡-中信卡","date":"2026-04-25","category":"餐點-晚餐","note":"牛鋤亭壽喜燒（中山站）","amount":7960,"currency":"TWD"},{"id":"1777219369416","type":"expense","account":"現金","date":"2026-04-26","category":"餐點-午餐","note":"老德記-炸麻麵","amount":120,"currency":"TWD"},{"id":"1777219406397","type":"expense","account":"信用卡-中信卡","date":"2026-04-26","category":"餐點-飲品","note":"摩斯漢堡-2杯可樂","amount":70,"currency":"TWD"},{"id":"1777219456486","type":"expense","account":"信用卡-中信卡","date":"2026-04-26","category":"餐點-飲品","note":"原萃-玄米綠茶+多多綠","amount":52,"currency":"TWD"},{"id":"1777250994609","type":"expense","account":"信用卡-中信卡","date":"2026-04-27","category":"餐點-飲品","note":"梅子綠茶","amount":40,"currency":"TWD"},{"id":"1777337854365","type":"expense","account":"現金","date":"2026-04-28","category":"餐點-午餐","note":"烏醋乾麵","amount":55,"currency":"TWD"},{"id":"1777337877841","type":"expense","account":"信用卡-中信卡","date":"2026-04-28","category":"餐點-飲品","note":"檸檬紅茶+比菲多","amount":78,"currency":"TWD"},{"id":"1777473271348","type":"expense","account":"信用卡-中信卡","date":"2026-04-29","category":"餐點-飲品","note":"檸檬紅茶+比菲多","amount":88,"currency":"TWD"},{"id":"1777473299332","type":"expense","account":"現金","date":"2026-04-29","category":"餐點-其他","note":"蒸餃","amount":210,"currency":"TWD"},{"id":"1777547492820","type":"expense","account":"信用卡-中信卡","date":"2026-04-30","category":"餐點-午餐","note":"泡麵","amount":53,"currency":"TWD"},{"id":"1777547529146","type":"expense","account":"信用卡-中信卡","date":"2026-04-30","category":"餐點-飲品","note":"梅子綠茶+百香多多","amount":80,"currency":"TWD"},{"id":"1777559165430","type":"expense","account":"信用卡-中信卡","date":"2026-04-30","category":"餐點-晚餐","note":"一蘭拉麵","amount":430,"currency":"TWD"},{"id":"1777559183030","type":"expense","account":"信用卡-中信卡","date":"2026-04-30","category":"餐點-飲品","note":"五桐號","amount":55,"currency":"TWD"},{"id":"1777577726265","type":"expense","account":"現金","date":"2026-04-30","category":"交通-大眾運輸","note":"TPASS","amount":1200,"currency":"TWD"},{"id":"1777692333261","type":"expense","account":"現金","date":"2026-05-02","category":"生活-電信費","note":"台哥大手機費","amount":1198,"currency":"TWD"},{"id":"1777692414022","type":"expense","account":"現金","date":"2026-05-02","category":"生活-信用卡費","note":"玉山卡費","amount":1484,"currency":"TWD"},{"id":"1777692681773","type":"expense","account":"現金","date":"2026-05-13","category":"投資-定期定額","note":"定期定額-0050","amount":2000,"currency":"TWD"},{"id":"1777692698264","type":"expense","account":"現金","date":"2026-05-13","category":"投資-定期定額","note":"定期定額-9816","amount":2000,"currency":"TWD"},{"id":"1777713027804","type":"expense","account":"信用卡-中信卡","date":"2026-05-02","category":"餐點-飲品","note":"原萃-玄米綠茶","amount":39,"currency":"TWD"},{"id":"1777720791521","type":"expense","account":"信用卡-中信卡","date":"2026-05-02","category":"餐點-其他","note":"士林夜市-炸彈蔥油餅","amount":65,"currency":"TWD"},{"id":"1777734332748","type":"expense","account":"現金","date":"2026-05-02","category":"餐點-晚餐","note":"芷鼎滷味","amount":145,"currency":"TWD"},{"id":"1777785823308","type":"expense","account":"信用卡-中信卡","date":"2026-05-03","category":"餐點-飲品","note":"淡水coffeinated coffee-咖啡拿鐵","amount":100,"currency":"TWD"},{"id":"1777785894776","type":"expense","account":"信用卡-中信卡","date":"2026-05-03","category":"餐點-午餐","note":"淡水祥記-香港的味道","amount":410,"currency":"TWD"},{"id":"1777796786330","type":"expense","account":"信用卡-中信卡","date":"2026-05-03","category":"餐點-飲品","note":"原萃玄米綠茶+多多綠","amount":69,"currency":"TWD"},{"id":"1777856291710","type":"expense","account":"信用卡-中信卡","date":"2026-05-04","category":"餐點-早餐","note":"御飯糰","amount":49,"currency":"TWD"},{"id":"1777856310021","type":"expense","account":"信用卡-中信卡","date":"2026-05-04","category":"餐點-飲品","note":"檸檬紅茶+比菲多","amount":88,"currency":"TWD"},{"id":"1777942551678","type":"expense","account":"信用卡-中信卡","date":"2026-05-05","category":"餐點-飲品","note":"梅子綠茶+比菲多","amount":88,"currency":"TWD"},{"id":"1777982317843","type":"expense","account":"信用卡-中信卡","date":"2026-05-05","category":"餐點-其他","note":"双響泡×2+科學麵×2","amount":82,"currency":"TWD"},{"id":"1778028680620","type":"expense","account":"信用卡-中信卡","date":"2026-05-06","category":"餐點-飲品","note":"梅子綠茶+百香多多","amount":80,"currency":"TWD"},{"id":"1778080642906","type":"expense","account":"信用卡-中信卡","date":"2026-05-06","category":"交通-加油","note":"無備註","amount":141,"currency":"TWD"},{"id":"1778114865518","type":"expense","account":"信用卡-中信卡","date":"2026-05-07","category":"餐點-飲品","note":"檸檬紅茶+比菲多","amount":88,"currency":"TWD"},{"id":"1778163510047","type":"expense","account":"現金","date":"2026-05-07","category":"餐點-晚餐","note":"茄汁蝦仁+牛肉烏龍","amount":210,"currency":"TWD"},{"id":"1778201957720","type":"expense","account":"信用卡-中信卡","date":"2026-05-08","category":"餐點-飲品","note":"檸檬紅茶","amount":50,"currency":"TWD"},{"id":"1778201974691","type":"expense","account":"現金","date":"2026-05-08","category":"餐點-午餐","note":"炒麵","amount":80,"currency":"TWD"},{"id":"1778425762627","type":"expense","account":"現金","date":"2026-05-24","category":"生活-房貸或房租","note":"無備註","amount":9280,"currency":"TWD"},{"id":"1778427553981","type":"expense","account":"現金","date":"2026-04-24","category":"生活-房貸或房租","note":"無備註","amount":9280,"currency":"TWD"},{"id":"1778427837231","type":"expense","account":"現金","date":"2026-06-13","category":"投資-定期定額","note":"0050","amount":2000,"currency":"TWD"},{"id":"1778427851584","type":"expense","account":"現金","date":"2026-06-13","category":"投資-定期定額","note":"9816","amount":2000,"currency":"TWD"},{"id":"1778460082180","type":"income","account":"系統入帳","date":"2026-05-10","category":"薪資-本薪","note":"無備註","amount":32877,"currency":"TWD"},{"id":"1778517260107","type":"expense","account":"信用卡-中信卡","date":"2026-05-11","category":"餐點-飲品","note":"原萃+比菲多","amount":80,"currency":"TWD"},{"id":"1778547314403","type":"expense","account":"信用卡-中信卡","date":"2026-05-12","category":"餐點-飲品","note":"梅子綠茶+百香多多","amount":80,"currency":"TWD"},{"id":"1778592390636","type":"income","account":"系統入帳","date":"2026-05-11","category":"薪資-獎金","note":"調薪？","amount":5000,"currency":"TWD"},{"id":"1778633302354","type":"expense","account":"信用卡-中信卡","date":"2026-05-13","category":"餐點-飲品","note":"原萃-玄米綠茶*2+多多綠","amount":69,"currency":"TWD"},{"id":"1778633326574","type":"expense","account":"現金","date":"2026-05-13","category":"餐點-午餐","note":"油飯","amount":80,"currency":"TWD"},{"id":"1778667391095","type":"expense","account":"現金","date":"2026-05-13","category":"餐點-其他","note":"滷味","amount":120,"currency":"TWD"},{"id":"1778806289995","type":"expense","account":"信用卡-中信卡","date":"2026-05-14","category":"餐點-飲品","note":"梅子綠茶","amount":50,"currency":"TWD"},{"id":"1778806324706","type":"expense","account":"信用卡-中信卡","date":"2026-05-15","category":"餐點-飲品","note":"原萃玄米綠茶×2","amount":39,"currency":"TWD"},{"id":"1778806351381","type":"expense","account":"現金","date":"2026-05-15","category":"餐點-早餐","note":"飯糰","amount":35,"currency":"TWD"},{"id":"1778806367108","type":"expense","account":"現金","date":"2026-05-15","category":"餐點-午餐","note":"油飯","amount":120,"currency":"TWD"},{"id":"1778806424431","type":"expense","account":"信用卡-中信卡","date":"2026-05-15","category":"餐點-飲品","note":"果汁牛奶+多多","amount":67,"currency":"TWD"},{"id":"1778852903815","type":"expense","account":"信用卡-中信卡","date":"2026-05-15","category":"餐點-其他","note":"滷味","amount":200,"currency":"TWD"},{"id":"1778904808007","type":"expense","account":"現金","date":"2026-05-16","category":"餐點-午餐","note":"牛肉拉麵2碗","amount":350,"currency":"TWD"},{"id":"1778904841602","type":"expense","account":"信用卡-中信卡","date":"2026-05-16","category":"餐點-飲品","note":"原萃-玄米綠茶×2","amount":39,"currency":"TWD"},{"id":"1778950086004","type":"expense","account":"現金","date":"2026-05-16","category":"生活-日用品","note":"裝咖啡豆的夾鏈袋","amount":22,"currency":"TWD"},{"id":"1778998829327","type":"expense","account":"信用卡-中信卡","date":"2026-05-17","category":"餐點-飲品","note":"十六茶","amount":29,"currency":"TWD"},{"id":"1778998849876","type":"expense","account":"信用卡-中信卡","date":"2026-05-17","category":"餐點-其他","note":"麥當勞","amount":193,"currency":"TWD"},{"id":"1779004066275","type":"expense","account":"現金","date":"2026-05-17","category":"餐點-其他","note":"老蔡水煎包","amount":100,"currency":"TWD"},{"id":"1779008881720","type":"expense","account":"信用卡-中信卡","date":"2026-05-17","category":"餐點-其他","note":"家樂福採買","amount":476,"currency":"TWD"},{"id":"1779008907070","type":"expense","account":"現金","date":"2026-05-17","category":"娛樂-其他","note":"大樂透","amount":50,"currency":"TWD"},{"id":"1779113746407","type":"expense","account":"信用卡-中信卡","date":"2026-05-18","category":"餐點-飲品","note":"檸檬紅茶+比菲多","amount":88,"currency":"TWD"},{"id":"1779116604479","type":"expense","account":"信用卡-中信卡","date":"2026-05-18","category":"其他","note":"南山長照保費","amount":10926,"currency":"TWD"},{"id":"1779192151528","type":"expense","account":"信用卡-中信卡","date":"2026-05-19","category":"餐點-飲品","note":"百香多多","amount":30,"currency":"TWD"},{"id":"1779192168451","type":"expense","account":"信用卡-中信卡","date":"2026-05-19","category":"餐點-飲品","note":"原萃","amount":42,"currency":"TWD"},{"id":"1779238329989","type":"expense","account":"現金","date":"2026-05-20","category":"餐點-午餐","note":"炒麵","amount":80,"currency":"TWD"},{"id":"1779238379233","type":"expense","account":"信用卡-中信卡","date":"2026-05-20","category":"餐點-飲品","note":"原萃-玄米綠茶*2+多多綠","amount":69,"currency":"TWD"},{"id":"1779288266050","type":"expense","account":"現金","date":"2026-05-20","category":"餐點-飲品","note":"布丁奶茶×2","amount":110,"currency":"TWD"},{"id":"1779368588488","type":"expense","account":"信用卡-中信卡","date":"2026-05-21","category":"餐點-飲品","note":"梅子綠茶+比菲多","amount":88,"currency":"TWD"},{"id":"1779411454120","type":"expense","account":"信用卡-中信卡","date":"2026-05-22","category":"餐點-飲品","note":"原萃+比菲多+多多綠","amount":122,"currency":"TWD"},{"id":"1779452063178","type":"expense","account":"現金","date":"2026-05-22","category":"餐點-晚餐","note":"茄汁羊肉炒飯","amount":160,"currency":"TWD"},{"id":"1779452189261","type":"expense","account":"信用卡-中信卡","date":"2026-05-22","category":"餐點-飲品","note":"YEBISU啤酒","amount":75,"currency":"TWD"},{"id":"1779590788585","type":"expense","account":"信用卡-中信卡","date":"2026-05-24","category":"餐點-飲品","note":"原萃玄米綠茶","amount":22,"currency":"TWD"},{"id":"1779599884663","type":"expense","account":"現金","date":"2026-05-24","category":"餐點-其他","note":"豆干+豆棗","amount":100,"currency":"TWD"},{"id":"1779599922737","type":"expense","account":"現金","date":"2026-05-24","category":"生活-其他","note":"手機架+洗杯用具","amount":59,"currency":"TWD"},{"id":"1779606217002","type":"expense","account":"現金","date":"2026-05-24","category":"餐點-晚餐","note":"牛肉拉麵+小菜","amount":465,"currency":"TWD"},{"id":"1779679842243","type":"expense","account":"信用卡-中信卡","date":"2026-05-25","category":"交通-加油","note":"無備註","amount":144,"currency":"TWD"},{"id":"1779679876177","type":"expense","account":"信用卡-中信卡","date":"2026-05-25","category":"生活-日用品","note":"沐浴露*2","amount":358,"currency":"TWD"},{"id":"1779756760302","type":"expense","account":"信用卡-中信卡","date":"2026-05-26","category":"餐點-飲品","note":"檸檬紅茶+比菲多","amount":88,"currency":"TWD"},{"id":"1779803925108","type":"expense","account":"信用卡-中信卡","date":"2026-05-26","category":"生活-其他","note":"浴室毛巾架","amount":999,"currency":"TWD"},{"id":"1779905968075","type":"expense","account":"信用卡-中信卡","date":"2026-05-27","category":"餐點-飲品","note":"檸檬紅茶+比菲多","amount":87,"currency":"TWD"},{"id":"1779906248528","type":"expense","account":"現金","date":"2026-05-27","category":"餐點-午餐","note":"烏醋乾麵","amount":55,"currency":"TWD"},{"id":"1779929136088","type":"expense","account":"信用卡-中信卡","date":"2026-05-28","category":"餐點-飲品","note":"檸檬紅茶+多多綠","amount":79,"currency":"TWD"},{"id":"1779929182424","type":"expense","account":"信用卡-中信卡","date":"2026-05-28","category":"餐點-早餐","note":"私房花雕雞腿排","amount":79,"currency":"TWD"},{"id":"1780015741238","type":"expense","account":"信用卡-中信卡","date":"2026-05-29","category":"餐點-早餐","note":"壽司","amount":79,"currency":"TWD"},{"id":"1780015767959","type":"expense","account":"信用卡-中信卡","date":"2026-05-29","category":"餐點-飲品","note":"梅子綠茶+百香多多","amount":79,"currency":"TWD"},{"id":"1780058404992","type":"expense","account":"信用卡-中信卡","date":"2026-05-29","category":"餐點-飲品","note":"原萃-玄米綠茶","amount":29,"currency":"TWD"},{"id":"1780062200230","type":"expense","account":"現金","date":"2026-05-29","category":"餐點-晚餐","note":"滷味","amount":310,"currency":"TWD"},{"id":"1780113661910","type":"expense","account":"信用卡-中信卡","date":"2026-05-30","category":"交通-大眾運輸","note":"TPass","amount":1200,"currency":"TWD"},{"id":"1780194980148","type":"expense","account":"信用卡-中信卡","date":"2026-05-31","category":"餐點-飲品","note":"礦泉水","amount":28,"currency":"TWD"},{"id":"1780201866799","type":"expense","account":"現金","date":"2026-05-31","category":"餐點-午餐","note":"富爸爸肉骨茶","amount":880,"currency":"TWD"},{"id":"1780201947187","type":"expense","account":"信用卡-中信卡","date":"2026-05-31","category":"餐點-飲品","note":"50嵐-四季春+布丁奶","amount":125,"currency":"TWD"},{"id":"1780209524233","type":"expense","account":"信用卡-中信卡","date":"2026-05-31","category":"餐點-飲品","note":"可可冰沙","amount":90,"currency":"TWD"},{"id":"1780221535961","type":"expense","account":"信用卡-中信卡","date":"2026-05-31","category":"餐點-飲品","note":"百事生可樂","amount":35,"currency":"TWD"},{"id":"1780272529577","type":"expense","account":"現金","date":"2026-05-31","category":"餐點-晚餐","note":"水煎包","amount":100,"currency":"TWD"},{"id":"1780275489811","type":"expense","account":"信用卡-中信卡","date":"2026-06-01","category":"餐點-早餐","note":"麵包","amount":25,"currency":"TWD"},{"id":"1780275511916","type":"expense","account":"信用卡-中信卡","date":"2026-06-01","category":"餐點-飲品","note":"原萃+美粒果","amount":70,"currency":"TWD"},{"id":"1780401224716","type":"expense","account":"信用卡-中信卡","date":"2026-06-02","category":"餐點-飲品","note":"鮮奶+生可樂+玄米綠茶","amount":91,"currency":"TWD"},{"id":"1780404196014","type":"expense","account":"信用卡-中信卡","date":"2026-06-02","category":"餐點-晚餐","note":"麥當勞套餐","amount":118,"currency":"TWD"},{"id":"1780447796342","type":"expense","account":"信用卡-中信卡","date":"2026-06-03","category":"餐點-飲品","note":"梅子綠茶+比菲多","amount":87,"currency":"TWD"},{"id":"1780447833785","type":"expense","account":"現金","date":"2026-06-03","category":"餐點-午餐","note":"油飯×3+飯糰","amount":155,"currency":"TWD"},{"id":"1780664556996","type":"expense","account":"信用卡-中信卡","date":"2026-06-04","category":"餐點-飲品","note":"百事生可樂","amount":45,"currency":"TWD"},{"id":"1780664594498","type":"expense","account":"現金","date":"2026-06-04","category":"餐點-晚餐","note":"羊肉炒烏龍","amount":110,"currency":"TWD"},{"id":"1780664619269","type":"expense","account":"信用卡-中信卡","date":"2026-06-05","category":"餐點-飲品","note":"檸檬紅茶+比菲多","amount":87,"currency":"TWD"},{"id":"1780664647432","type":"expense","account":"信用卡-中信卡","date":"2026-06-05","category":"餐點-飲品","note":"鮮奶","amount":35,"currency":"TWD"},{"id":"1780664668551","type":"expense","account":"現金","date":"2026-06-05","category":"餐點-午餐","note":"烏醋乾麵","amount":55,"currency":"TWD"},{"id":"1780664682960","type":"expense","account":"現金","date":"2026-06-05","category":"餐點-晚餐","note":"滷味","amount":105,"currency":"TWD"},{"id":"1780721318969","type":"expense","account":"信用卡-中信卡","date":"2026-06-06","category":"餐點-飲品","note":"原萃玄米綠茶","amount":29,"currency":"TWD"},{"id":"1780731839467","type":"expense","account":"現金","date":"2026-06-06","category":"生活-日用品","note":"雨衣","amount":890,"currency":"TWD"},{"id":"1780734970628","type":"expense","account":"信用卡-中信卡","date":"2026-06-06","category":"餐點-晚餐","note":"三顧茅廬滷味","amount":170,"currency":"TWD"},{"id":"1780757612788","type":"expense","account":"現金","date":"2026-06-01","category":"生活-電信費","note":"台灣大","amount":1198,"currency":"TWD"},{"id":"1780757648374","type":"expense","account":"現金","date":"2026-06-01","category":"生活-信用卡費","note":"玉山卡費","amount":1484,"currency":"TWD"},{"id":"1780757756470","type":"income","account":"系統入帳","date":"2026-06-10","category":"薪資-本薪","note":"無備註","amount":31651,"currency":"TWD"},{"id":"1780811265721","type":"expense","account":"信用卡-中信卡","date":"2026-06-07","category":"餐點-飲品","note":"礦泉水","amount":56,"currency":"TWD"},{"id":"1780811292734","type":"expense","account":"現金","date":"2026-06-07","category":"餐點-午餐","note":"老蔡水煎包","amount":100,"currency":"TWD"},{"id":"1780845255937","type":"expense","account":"信用卡-中信卡","date":"2026-06-07","category":"餐點-飲品","note":"百事生可樂","amount":45,"currency":"TWD"},{"id":"1780879987634","type":"expense","account":"信用卡-中信卡","date":"2026-06-08","category":"餐點-飲品","note":"鮮奶+玄米綠茶","amount":56,"currency":"TWD"},{"id":"1780891357894","type":"income","account":"系統入帳","date":"2026-06-08","category":"其他收入-中獎","note":"3、4月發票中獎","amount":2000,"currency":"TWD"},{"id":"1780891465708","type":"income","account":"系統入帳","date":"2026-04-06","category":"其他收入-中獎","note":"1、2月發票中獎","amount":1000,"currency":"TWD"},{"id":"1781104185312","type":"expense","account":"信用卡-中信卡","date":"2026-06-09","category":"餐點-早餐","note":"奶酥麵包","amount":28,"currency":"TWD"},{"id":"1781104294738","type":"expense","account":"信用卡-中信卡","date":"2026-06-09","category":"餐點-飲品","note":"日東皇家奶茶（優惠-$7）+礦泉水","amount":67,"currency":"TWD"},{"id":"1781104336323","type":"expense","account":"信用卡-中信卡","date":"2026-06-10","category":"餐點-午餐","note":"雙響砲","amount":35,"currency":"TWD"},{"id":"1781104397907","type":"expense","account":"信用卡-中信卡","date":"2026-06-10","category":"餐點-飲品","note":"日東皇家奶茶（優惠-$7）+多多綠","amount":62,"currency":"TWD"},{"id":"1781104420847","type":"expense","account":"現金","date":"2026-06-10","category":"餐點-其他","note":"蒸餃","amount":210,"currency":"TWD"},{"id":"1781138693662","type":"expense","account":"信用卡-中信卡","date":"2026-06-11","category":"餐點-飲品","note":"檸檬紅茶+比菲多","amount":87,"currency":"TWD"},{"id":"1781138706715","type":"expense","account":"信用卡-中信卡","date":"2026-06-11","category":"交通-加油","note":"無備註","amount":151,"currency":"TWD"},{"id":"1781225287012","type":"expense","account":"信用卡-中信卡","date":"2026-06-12","category":"餐點-飲品","note":"百香多多","amount":30,"currency":"TWD"},{"id":"1781225303367","type":"expense","account":"信用卡-中信卡","date":"2026-06-12","category":"餐點-飲品","note":"原萃","amount":42,"currency":"TWD"},{"id":"1781225318705","type":"expense","account":"現金","date":"2026-06-12","category":"餐點-午餐","note":"烏醋乾麵","amount":55,"currency":"TWD"},{"id":"1781274764442","type":"expense","account":"現金","date":"2026-06-12","category":"餐點-飲品","note":"布丁奶茶+綠豆沙牛奶","amount":105,"currency":"TWD"},{"id":"1781274790897","type":"income","account":"系統入帳","date":"2026-06-12","category":"薪資-本薪","note":"無備註","amount":5000,"currency":"TWD"},{"id":"1781331340432","type":"expense","account":"信用卡-中信卡","date":"2026-06-13","category":"餐點-飲品","note":"礦泉水+ おーいお茶","amount":63,"currency":"TWD"},{"id":"1781334419523","type":"expense","account":"現金","date":"2026-06-13","category":"餐點-晚餐","note":"大半筋半肉+小牛肉拉麵","amount":410,"currency":"TWD"},{"id":"1781338249336","type":"expense","account":"信用卡-中信卡","date":"2026-06-13","category":"餐點-飲品","note":"義美奶茶","amount":45,"currency":"TWD"},{"id":"1781342904689","type":"expense","account":"信用卡-中信卡","date":"2026-06-13","category":"餐點-飲品","note":"百事生可樂","amount":45,"currency":"TWD"},{"id":"1781413606725","type":"expense","account":"現金","date":"2026-06-24","category":"生活-房貸或房租","note":"無備註","amount":9280,"currency":"TWD"},{"id":"1781484518217","type":"expense","account":"信用卡-中信卡","date":"2026-06-15","category":"餐點-飲品","note":"綾鷹×2","amount":78,"currency":"TWD"},{"id":"1781534744969","type":"expense","account":"信用卡-中信卡","date":"2026-06-16","category":"餐點-午餐","note":"雙響砲+牛肉麵","amount":53,"currency":"TWD"},{"id":"1781571610468","type":"expense","account":"現金","date":"2026-06-16","category":"餐點-午餐","note":"烏醋乾麵","amount":55,"currency":"TWD"},{"id":"1781622202104","type":"expense","account":"信用卡-中信卡","date":"2026-06-16","category":"餐點-飲品","note":"檸檬紅茶+比菲多","amount":87,"currency":"TWD"},{"id":"1781657193066","type":"expense","account":"信用卡-中信卡","date":"2026-06-17","category":"餐點-飲品","note":"玄米茶+柚子茶+梅子綠茶","amount":107,"currency":"TWD"},{"id":"1781691227517","type":"expense","account":"現金","date":"2026-06-17","category":"餐點-其他","note":"滷味","amount":110,"currency":"TWD"},{"id":"1781743979233","type":"expense","account":"現金","date":"2026-06-18","category":"餐點-午餐","note":"油飯×2+飯糰","amount":110,"currency":"TWD"},{"id":"1781744026683","type":"expense","account":"信用卡-中信卡","date":"2026-06-18","category":"餐點-飲品","note":"日東皇家奶茶（優惠-$5）","amount":59,"currency":"TWD"},{"id":"1781800769103","type":"expense","account":"信用卡-中信卡","date":"2026-06-18","category":"餐點-飲品","note":"義美奶茶","amount":45,"currency":"TWD"},{"id":"1781800835039","type":"expense","account":"信用卡-中信卡","date":"2026-06-18","category":"餐點-晚餐","note":"茶葉蛋*2*握手捲","amount":79,"currency":"TWD"},{"id":"1781927592112","type":"expense","account":"信用卡-中信卡","date":"2026-06-20","category":"餐點-午餐","note":"麥當勞","amount":336,"currency":"TWD"},{"id":"1781961692696","type":"expense","account":"信用卡-中信卡","date":"2026-06-20","category":"餐點-飲品","note":"ゆす茶","amount":39,"currency":"TWD"},{"id":"1781961795627","type":"expense","account":"信用卡-中信卡","date":"2026-06-20","category":"餐點-其他","note":"家樂福採買（鮮奶茶+炒麵醬+檸檬芭樂）","amount":203,"currency":"TWD"},{"id":"1781961824626","type":"expense","account":"信用卡-中信卡","date":"2026-06-20","category":"餐點-其他","note":"統一布丁（大）","amount":20,"currency":"TWD"},{"id":"1782026143122","type":"expense","account":"信用卡-中信卡","date":"2026-06-21","category":"餐點-飲品","note":"礦泉水","amount":57,"currency":"TWD"},{"id":"1782026209319","type":"expense","account":"現金","date":"2026-06-21","category":"餐點-午餐","note":"中原香豬腳麵線+滷肉飯+小菜","amount":240,"currency":"TWD"},{"id":"1782026233939","type":"expense","account":"信用卡-中信卡","date":"2026-06-21","category":"生活-日用品","note":"寶雅買面膜","amount":123,"currency":"TWD"},{"id":"1782026288369","type":"expense","account":"信用卡-中信卡","date":"2026-06-21","category":"餐點-飲品","note":"龜甲萬紅茶，買一送一","amount":160,"currency":"TWD"},{"id":"1782026380469","type":"expense","account":"信用卡-中信卡","date":"2026-06-21","category":"餐點-其他","note":"鰻魚片4片*160+蟹肉棒10根*570","amount":730,"currency":"TWD"},{"id":"1782089420812","type":"expense","account":"信用卡-中信卡","date":"2026-06-22","category":"餐點-飲品","note":"綾鷹","amount":39,"currency":"TWD"},{"id":"1782130233511","type":"expense","account":"信用卡-中信卡","date":"2026-06-22","category":"餐點-晚餐","note":"桶好呷滷味","amount":140,"currency":"TWD"},{"id":"1782175689102","type":"expense","account":"信用卡-中信卡","date":"2026-06-23","category":"餐點-飲品","note":"檸檬紅茶+比菲多","amount":87,"currency":"TWD"},{"id":"1782261706079","type":"expense","account":"現金","date":"2026-06-24","category":"餐點-午餐","note":"炒麵","amount":60,"currency":"TWD"},{"id":"1782261753867","type":"expense","account":"信用卡-中信卡","date":"2026-06-24","category":"餐點-早餐","note":"萊爾富麵包","amount":35,"currency":"TWD"},{"id":"1782261859870","type":"expense","account":"信用卡-中信卡","date":"2026-06-24","category":"餐點-飲品","note":"ゆす茶*2（優惠-$12）","amount":78,"currency":"TWD"},{"id":"1782348886789","type":"expense","account":"信用卡-中信卡","date":"2026-06-25","category":"餐點-飲品","note":"原萃-玄米綠茶","amount":29,"currency":"TWD"},{"id":"1782471175942","type":"expense","account":"現金","date":"2026-06-26","category":"餐點-午餐","note":"烏醋乾麵","amount":55,"currency":"TWD"},{"id":"1782471196002","type":"expense","account":"信用卡-中信卡","date":"2026-06-26","category":"餐點-飲品","note":"義美奶茶","amount":45,"currency":"TWD"},{"id":"1782491221450","type":"expense","account":"現金","date":"2026-06-26","category":"餐點-飲品","note":"成都楊桃汁","amount":50,"currency":"TWD"},{"id":"1782491249877","type":"expense","account":"現金","date":"2026-06-26","category":"娛樂-影音","note":"柯南劇場版","amount":340,"currency":"TWD"},{"id":"1782491305440","type":"expense","account":"信用卡-中信卡","date":"2026-06-27","category":"餐點-其他","note":"黑胡椒烤雞握便當","amount":59,"currency":"TWD"},{"id":"1782549801790","type":"expense","account":"現金","date":"2026-06-27","category":"娛樂-其他","note":"星光大道會員卡","amount":300,"currency":"TWD"},{"id":"1782549830112","type":"expense","account":"現金","date":"2026-06-27","category":"娛樂-其他","note":"星光大道唱歌","amount":500,"currency":"TWD"},{"id":"1782549849044","type":"expense","account":"現金","date":"2026-06-27","category":"餐點-其他","note":"原滷味","amount":200,"currency":"TWD"},{"id":"1782629317308","type":"expense","account":"信用卡-中信卡","date":"2026-06-28","category":"餐點-飲品","note":"日東紅茶花傳","amount":35,"currency":"TWD"},{"id":"1782629351172","type":"expense","account":"信用卡-中信卡","date":"2026-06-28","category":"餐點-飲品","note":"純喫茶-芭樂綠茶","amount":25,"currency":"TWD"},{"id":"1782639463753","type":"expense","account":"現金","date":"2026-06-28","category":"餐點-飲品","note":"咖啡豆","amount":600,"currency":"TWD"},{"id":"1782639510412","type":"expense","account":"信用卡-中信卡","date":"2026-06-28","category":"餐點-晚餐","note":"麗媽沙茶鍋","amount":180,"currency":"TWD"},{"id":"1782644038311","type":"expense","account":"信用卡-中信卡","date":"2026-06-28","category":"餐點-飲品","note":"多多綠茶","amount":30,"currency":"TWD"},{"id":"1782721139257","type":"expense","account":"現金","date":"2026-06-29","category":"生活-其他","note":"看牙醫(補牙洞+洗牙)","amount":150,"currency":"TWD"},{"id":"1782721156832","type":"expense","account":"信用卡-中信卡","date":"2026-06-29","category":"交通-加油","note":"無備註","amount":128,"currency":"TWD"},{"id":"1782721360886","type":"expense","account":"現金","date":"2026-06-28","category":"其他","note":"大樂透","amount":50,"currency":"TWD"},{"id":"1782721416756","type":"expense","account":"信用卡-中信卡","date":"2026-06-29","category":"餐點-飲品","note":"統一布丁(小*3)+日東皇家奶茶","amount":86,"currency":"TWD"},{"id":"1782722264373","type":"income","account":"系統入帳","date":"2026-06-29","category":"投資-利息","note":"股票借券利息","amount":14,"currency":"TWD"},{"id":"1782722521559","type":"expense","account":"現金","date":"2026-07-01","category":"生活-信用卡費","note":"玉山卡費","amount":1484,"currency":"TWD"},{"id":"1782722711302","type":"expense","account":"現金","date":"2026-07-01","category":"生活-電信費","note":" 台哥大手機費","amount":1267,"currency":"TWD"},{"id":"1782722738222","type":"expense","account":"現金","date":"2026-07-24","category":"生活-房貸或房租","note":"無備註","amount":9280,"currency":"TWD"},{"id":"1782722768519","type":"expense","account":"現金","date":"2026-07-13","category":"投資-定期定額","note":"0050","amount":2000,"currency":"TWD"},{"id":"1782722791849","type":"expense","account":"現金","date":"2026-07-13","category":"投資-定期定額","note":"009816","amount":2000,"currency":"TWD"},{"id":"1782780670374","type":"expense","account":"信用卡-中信卡","date":"2026-06-30","category":"餐點-飲品","note":"日東皇家奶茶（優惠-$7）","amount":32,"currency":"TWD"},{"id":"1782866857021","type":"expense","account":"現金","date":"2026-07-01","category":"餐點-午餐","note":"烏醋乾麵","amount":55,"currency":"TWD"},{"id":"1782866870481","type":"expense","account":"信用卡-中信卡","date":"2026-07-01","category":"餐點-飲品","note":"檸檬紅茶+比菲多","amount":81,"currency":"TWD"},{"id":"1782953325122","type":"expense","account":"信用卡-中信卡","date":"2026-07-02","category":"餐點-飲品","note":"綾鷹+ゆず茶","amount":78,"currency":"TWD"},{"id":"1783072401886","type":"expense","account":"現金","date":"2026-07-03","category":"餐點-午餐","note":"油飯×2+飯糰","amount":115,"currency":"TWD"},{"id":"1783072416627","type":"expense","account":"信用卡-中信卡","date":"2026-07-03","category":"餐點-飲品","note":"百事生可樂","amount":45,"currency":"TWD"},{"id":"1783072464270","type":"expense","account":"現金","date":"2026-07-02","category":"餐點-其他","note":"咖哩羊肉炒烏龍","amount":110,"currency":"TWD"},{"id":"1783155179553","type":"expense","account":"信用卡-中信卡","date":"2026-07-04","category":"餐點-飲品","note":"西雅圖咖啡","amount":190,"currency":"TWD"},{"id":"1783155212745","type":"expense","account":"現金","date":"2026-07-04","category":"餐點-晚餐","note":"牛肉拉麵+小菜","amount":475,"currency":"TWD"},{"id":"1783155458998","type":"expense","account":"信用卡-中信卡","date":"2026-07-03","category":"餐點-其他","note":"黑胡椒烤雞握便當+茶葉蛋×2","amount":58,"currency":"TWD"},{"id":"1783158228748","type":"expense","account":"信用卡-中信卡","date":"2026-07-04","category":"餐點-飲品","note":"原萃玄米綠茶","amount":29,"currency":"TWD"},{"id":"1783247651438","type":"expense","account":"信用卡-中信卡","date":"2026-07-05","category":"生活-日用品","note":"家樂福採買","amount":554,"currency":"TWD"},{"id":"1783309192132","type":"expense","account":"信用卡-中信卡","date":"2026-07-05","category":"生活-其他","note":"防水膠帶","amount":799,"currency":"TWD"},{"id":"1783309253742","type":"expense","account":"信用卡-中信卡","date":"2026-07-05","category":"餐點-其他","note":"統一布丁（小）","amount":36,"currency":"TWD"},{"id":"1783309291809","type":"income","account":"系統入帳","date":"2026-07-05","category":"其他收入-其他","note":"無備註","amount":500,"currency":"TWD"},{"id":"1783309346803","type":"expense","account":"信用卡-中信卡","date":"2026-07-05","category":"餐點-午餐","note":"溫州老虎醬-餛飩麵+餛飩湯+炸醬麵","amount":275,"currency":"TWD"},{"id":"1783309399156","type":"expense","account":"信用卡-中信卡","date":"2026-07-06","category":"餐點-飲品","note":"原萃玄米綠茶+純喫茶-芭樂綠茶","amount":54,"currency":"TWD"},{"id":"1783341482872","type":"expense","account":"信用卡-中信卡","date":"2026-07-06","category":"餐點-晚餐","note":"全家超商飯糰×3","amount":169,"currency":"TWD"},{"id":"1783385374043","type":"expense","account":"信用卡-中信卡","date":"2026-07-03","category":"交通-大眾運輸","note":"TPass","amount":1179,"currency":"TWD"},{"id":"1783440671905","type":"expense","account":"信用卡-中信卡","date":"2026-07-07","category":"餐點-晚餐","note":"桶好呷滷味","amount":210,"currency":"TWD"},{"id":"1783472048048","type":"expense","account":"信用卡-中信卡","date":"2026-07-08","category":"餐點-飲品","note":"玄米茶+ゆず茶","amount":78,"currency":"TWD"},{"id":"1783472061390","type":"expense","account":"現金","date":"2026-07-08","category":"餐點-午餐","note":"烏醋乾麵","amount":55,"currency":"TWD"},{"id":"1783472104116","type":"income","account":"系統入帳","date":"2026-07-13","category":"投資-利息","note":"00919","amount":20165,"currency":"TWD"},{"id":"1783515764681","type":"expense","account":"信用卡-中信卡","date":"2026-07-08","category":"餐點-飲品","note":"十六茶","amount":29,"currency":"TWD"},{"id":"1783515825894","type":"expense","account":"信用卡-中信卡","date":"2026-07-08","category":"餐點-其他","note":"家樂福-炸腿肉","amount":39,"currency":"TWD"},{"id":"1783515874311","type":"expense","account":"信用卡-中信卡","date":"2026-07-09","category":"餐點-早餐","note":"家樂福-奶酥菠蘿麵包","amount":41,"currency":"TWD"},{"id":"1783515919463","type":"expense","account":"信用卡-中信卡","date":"2026-07-08","category":"餐點-飲品","note":"家樂福-原萃玄米綠茶×4","amount":78,"currency":"TWD"},{"id":"1783598076093","type":"expense","account":"信用卡-中信卡","date":"2026-07-09","category":"餐點-飲品","note":"十六茶","amount":29,"currency":"TWD"},{"id":"1783598108144","type":"expense","account":"信用卡-中信卡","date":"2026-07-09","category":"餐點-晚餐","note":"麥當勞套餐","amount":148,"currency":"TWD"},{"id":"1783756147864","type":"expense","account":"信用卡-中信卡","date":"2026-07-09","category":"餐點-其他","note":"二師兄-肉羹麵","amount":75,"currency":"TWD"},{"id":"1783756214159","type":"income","account":"系統入帳","date":"2026-07-10","category":"薪資-本薪","note":"多1000，端午獎金？","amount":38406,"currency":"TWD"},{"id":"1783990723974","type":"expense","account":"信用卡-中信卡","date":"2026-07-12","category":"餐點-飲品","note":"礦泉水","amount":28,"currency":"TWD"},{"id":"1783990752155","type":"expense","account":"現金","date":"2026-07-12","category":"餐點-其他","note":"老蔡水煎包","amount":100,"currency":"TWD"},{"id":"1783990780044","type":"expense","account":"信用卡-中信卡","date":"2026-07-12","category":"餐點-其他","note":"家樂福-奶酥菠蘿麵包","amount":104,"currency":"TWD"},{"id":"1783990814206","type":"expense","account":"信用卡-中信卡","date":"2026-07-12","category":"餐點-飲品","note":"百事生可樂-檸檬口味","amount":35,"currency":"TWD"},{"id":"1783990858781","type":"expense","account":"信用卡-中信卡","date":"2026-07-13","category":"生活-日用品","note":"家樂福採買","amount":376,"currency":"TWD"},{"id":"1783990915077","type":"expense","account":"信用卡-中信卡","date":"2026-07-14","category":"餐點-飲品","note":"黑豆水×$50+原萃-玄米綠茶","amount":79,"currency":"TWD"},{"id":"1784024367175","type":"expense","account":"現金","date":"2026-07-14","category":"餐點-其他","note":"滷味","amount":100,"currency":"TWD"},{"id":"1784024401393","type":"income","account":"系統入帳","date":"2026-07-14","category":"薪資-獎金","note":"生日禮金補發","amount":1000,"currency":"TWD"},{"id":"1784076763721","type":"expense","account":"現金","date":"2026-07-15","category":"餐點-午餐","note":"烏醋乾麵","amount":55,"currency":"TWD"},{"id":"1784076803013","type":"expense","account":"信用卡-中信卡","date":"2026-07-15","category":"餐點-飲品","note":"原萃-玄米綠茶+日東皇家奶茶","amount":61,"currency":"TWD"},{"id":"1784162827973","type":"expense","account":"信用卡-中信卡","date":"2026-07-16","category":"餐點-飲品","note":"檸檬紅茶+比菲多","amount":81,"currency":"TWD"},{"id":"1784217255743","type":"expense","account":"現金","date":"2026-07-16","category":"餐點-晚餐","note":"紅燒臭豆腐麵","amount":120,"currency":"TWD"},{"id":"1784287773231","type":"expense","account":"信用卡-中信卡","date":"2026-07-17","category":"餐點-飲品","note":"原萃玄米綠茶×2","amount":52,"currency":"TWD"},{"id":"1784287788412","type":"expense","account":"信用卡-中信卡","date":"2026-07-17","category":"交通-加油","note":"無備註","amount":130,"currency":"TWD"},{"id":"1784287809079","type":"expense","account":"現金","date":"2026-07-17","category":"餐點-午餐","note":"油飯×2+飯糰","amount":115,"currency":"TWD"},{"id":"1784460921030","type":"expense","account":"信用卡-中信卡","date":"2026-07-17","category":"餐點-飲品","note":"百事生可樂-檸檬口味","amount":35,"currency":"TWD"},{"id":"1784460976036","type":"expense","account":"信用卡-中信卡","date":"2026-07-19","category":"餐點-早餐","note":"原萃-玉露","amount":29,"currency":"TWD"},{"id":"1784461024604","type":"expense","account":"信用卡-中信卡","date":"2026-07-19","category":"餐點-其他","note":"十二廚餐卷×6","amount":7794,"currency":"TWD"},{"id":"1784461048481","type":"expense","account":"信用卡-中信卡","date":"2026-07-19","category":"餐點-飲品","note":"百事生可樂-檸檬口味","amount":27,"currency":"TWD"},{"id":"1784461084719","type":"expense","account":"現金","date":"2026-07-19","category":"餐點-晚餐","note":"老虎醬餛飩麵","amount":305,"currency":"TWD"},{"id":"1784595019368","type":"expense","account":"信用卡-中信卡","date":"2026-07-20","category":"餐點-飲品","note":"原萃玄米綠茶+波蜜","amount":52,"currency":"TWD"},{"id":"1784595058033","type":"expense","account":"信用卡-中信卡","date":"2026-07-21","category":"餐點-飲品","note":"原萃玄米綠茶+日東皇家奶茶","amount":54,"currency":"TWD"},{"id":"1784681410097","type":"expense","account":"現金","date":"2026-07-22","category":"餐點-午餐","note":"炒麵","amount":80,"currency":"TWD"},{"id":"1784681454629","type":"expense","account":"信用卡-中信卡","date":"2026-07-22","category":"餐點-飲品","note":"萊爾富-boss微奢奶茶","amount":98,"currency":"TWD"},{"id":"1784733819482","type":"expense","account":"信用卡-中信卡","date":"2026-07-22","category":"餐點-其他","note":"純喫茶+茶葉蛋×2","amount":45,"currency":"TWD"},{"id":"1784767583393","type":"expense","account":"信用卡-中信卡","date":"2026-07-23","category":"餐點-飲品","note":"檸檬紅茶+比菲多","amount":72,"currency":"TWD"}]